{"resource_usage":{"memory":{"system_total":67157626880,"peak_rss_bytes":6535770112},"garbage_collection":{"count":31,"total_secs":3.178},"cpu":{"load":8.606047630698965,"total_cores":12}},"image_details":{"code_area":{"bytes":23943120,"compilation_units":39399},"total_bytes":49056424,"image_heap":{"bytes":24772608,"resources":{"bytes":402652,"count":12}}},"general_info":{"c_compiler":"gcc (redhat, x86_64, 8.5.0)","name":"todos-1.0.0-SNAPSHOT-runner","java_version":"17.0.7+7","garbage_collector":"Serial GC","graalvm_version":"GraalVM 22.3.2.1-Final Java 17 Mandrel Distribution"},"analysis_results":{"methods":{"total":108577,"reflection":2750,"jni":55,"reachable":61298},"classes":{"total":13808,"reflection":561,"jni":63,"reachable":12283},"fields":{"total":29388,"reflection":111,"jni":68,"reachable":17240}}}
